[
    {
        "": "0",
        "Tanggal": "01-12-2020",
        "Waktu": "11:30:00Z\t",
        "Lat": "-2.2266666666666666",
        "Long": "113.94388888888888",
        "ICAO": "Stamet Tjilik Riwut - Palangkaraya (WAGG)",
        "Angin": "21006KT",
        "Visibility": "9999",
        "Cuaca": "SCT011"
    },
    {
        "": "1",
        "Tanggal": "01-12-2020",
        "Waktu": "11:30:00Z\t",
        "Lat": "0.46",
        "Long": "101.44388888888888",
        "ICAO": "Stamet I Sultan Syarif Kasim II - Pekanbaru (WIBB)",
        "Angin": "34005KT",
        "Visibility": "9000",
        "Cuaca": "FEW017"
    },
    {
        "": "2",
        "Tanggal": "01-12-2020",
        "Waktu": "11:30:00Z\t",
        "Lat": "-1.630466",
        "Long": "103.642847",
        "ICAO": "Stamet I Sultan Thaha - Jambi (WIJJ)",
        "Angin": "35002KT",
        "Visibility": "9000",
        "Cuaca": "FEW018"
    },
    {
        "": "3",
        "Tanggal": "01-12-2020",
        "Waktu": "11:30:00Z\t",
        "Lat": "-0.14888888888888888",
        "Long": "109.4027777777778",
        "ICAO": "Stamet I Supadio - Pontianak (WIOO)",
        "Angin": "00000KT",
        "Visibility": "6000",
        "Cuaca": "FEW012"
    },
    {
        "": "4",
        "Tanggal": "01-12-2020",
        "Waktu": "11:30:00Z\t",
        "Lat": "-2.8977777777777787",
        "Long": "104.70083333333334",
        "ICAO": "Sultan Mahmud Badaruddin II - Palembang (WIPP)",
        "Angin": "30003KT",
        "Visibility": "9999",
        "Cuaca": "FEW010"
    }
]